{
  "$schema": "http://json-schema.org/draft-04/schema#",
  "title": "structured log schema",
  "description": "json schema for the cloudwatch agent k8s structured log",
  "type": "object",

  "properties": {
    "ClusterName":{},
    "Type":{},
    "Sources":{},
    "Timestamp":{},
    "Version":{},
    "AutoScalingGroupName":{},
    "InstanceId":{},
    "InstanceType":{},
    "NodeName":{},
    "PodName":{},
    "Namespace":{},
    "pod_cpu_usage_system":{},
    "pod_cpu_usage_total":{},
    "pod_cpu_usage_user":{},
    "pod_cpu_utilization":{},
    "pod_memory_cache":{},
    "pod_memory_failcnt":{},
    "pod_memory_hierarchical_pgfault":{},
    "pod_memory_hierarchical_pgmajfault":{},
    "pod_memory_mapped_file":{},
    "pod_memory_max_usage":{},
    "pod_memory_pgfault":{},
    "pod_memory_pgmajfault":{},
    "pod_memory_rss":{},
    "pod_memory_swap":{},
    "pod_memory_usage":{},
    "pod_memory_utilization":{},
    "pod_memory_working_set":{},
    "pod_network_rx_bytes":{},
    "pod_network_rx_dropped":{},
    "pod_network_rx_errors":{},
    "pod_network_rx_packets":{},
    "pod_network_total_bytes":{},
    "pod_network_tx_bytes":{},
    "pod_network_tx_dropped":{},
    "pod_network_tx_errors":{},
    "pod_network_tx_packets":{},
    "pod_number_of_running_containers":{},
    "pod_number_of_containers":{},
    "pod_number_of_container_restarts":{},
    "pod_status":{},
    "kubernetes":{
      "type": "object",
      "properties": {
        "host": {},
        "labels": {},
        "namespace_name":{},
        "pod_id":{},
        "pod_name":{},
        "pod_owners":{},
        "service_name":{}
      },
      "required": ["host","namespace_name","pod_id","pod_name"],
      "additionalProperties": false
    },
    "Service":{},
    "pod_cpu_limit": {},
    "pod_memory_limit": {},
    "pod_cpu_request":{},
    "pod_cpu_reserved_capacity":{},
    "pod_cpu_utilization_over_pod_limit":{},
    "pod_memory_request":{},
    "pod_memory_reserved_capacity":{},
    "pod_memory_utilization_over_pod_limit":{},
    "_aws": {
      "properties": {
        "CloudWatchMetrics": {},
        "Timestamp": {}
      },
      "required": [
        "CloudWatchMetrics",
        "Timestamp"
      ]
    }
  },
  "required": [
    "ClusterName",
    "Type",
    "Sources",
    "Timestamp",
    "Version",
    "AutoScalingGroupName",
    "InstanceId",
    "InstanceType",
    "NodeName",
    "PodName",
    "Namespace",
    "kubernetes",
    "pod_cpu_usage_system",
    "pod_cpu_usage_total",
    "pod_cpu_usage_user",
    "pod_cpu_utilization",
    "pod_memory_cache",
    "pod_memory_failcnt",
    "pod_memory_hierarchical_pgfault",
    "pod_memory_hierarchical_pgmajfault",
    "pod_memory_mapped_file",
    "pod_memory_max_usage",
    "pod_memory_pgfault",
    "pod_memory_pgmajfault",
    "pod_memory_rss",
    "pod_memory_swap",
    "pod_memory_usage",
    "pod_memory_utilization",
    "pod_memory_working_set",
    "pod_network_rx_bytes",
    "pod_network_rx_dropped",
    "pod_network_rx_errors",
    "pod_network_rx_packets",
    "pod_network_total_bytes",
    "pod_network_tx_bytes",
    "pod_network_tx_dropped",
    "pod_network_tx_errors",
    "pod_network_tx_packets",
    "pod_number_of_running_containers",
    "pod_number_of_containers",
    "pod_number_of_container_restarts",
    "pod_status",
    "_aws"
  ],
  "additionalProperties": false
}